gepa_observable/__init__.py
gepa_observable/_lm_integration.py
gepa_observable/_version.py
gepa_observable/api.py
gepa_observable/gepa.py
gepa_observable/gepa_utils.py
gepa_observable/observers.py
gepa_observable/adapters/__init__.py
gepa_observable/adapters/anymaths_adapter/__init__.py
gepa_observable/adapters/anymaths_adapter/anymaths_adapter.py
gepa_observable/adapters/default_adapter/__init__.py
gepa_observable/adapters/default_adapter/default_adapter.py
gepa_observable/adapters/dspy_adapter/__init__.py
gepa_observable/adapters/dspy_adapter/dspy_adapter.py
gepa_observable/adapters/dspy_full_program_adapter/dspy_program_proposal_signature.py
gepa_observable/adapters/dspy_full_program_adapter/full_program_adapter.py
gepa_observable/adapters/generic_rag_adapter/__init__.py
gepa_observable/adapters/generic_rag_adapter/evaluation_metrics.py
gepa_observable/adapters/generic_rag_adapter/generic_rag_adapter.py
gepa_observable/adapters/generic_rag_adapter/rag_pipeline.py
gepa_observable/adapters/generic_rag_adapter/vector_store_interface.py
gepa_observable/adapters/generic_rag_adapter/vector_stores/__init__.py
gepa_observable/adapters/generic_rag_adapter/vector_stores/chroma_store.py
gepa_observable/adapters/generic_rag_adapter/vector_stores/lancedb_store.py
gepa_observable/adapters/generic_rag_adapter/vector_stores/milvus_store.py
gepa_observable/adapters/generic_rag_adapter/vector_stores/qdrant_store.py
gepa_observable/adapters/generic_rag_adapter/vector_stores/weaviate_store.py
gepa_observable/adapters/terminal_bench_adapter/__init__.py
gepa_observable/adapters/terminal_bench_adapter/terminal_bench_adapter.py
gepa_observable/core/__init__.py
gepa_observable/core/adapter.py
gepa_observable/core/context.py
gepa_observable/core/data_loader.py
gepa_observable/core/engine.py
gepa_observable/core/lm_logger.py
gepa_observable/core/result.py
gepa_observable/core/serialization.py
gepa_observable/core/state.py
gepa_observable/logging/__init__.py
dspy_gepa_logger-0.2.0a0.dist-info/METADATA
dspy_gepa_logger-0.2.0a0.dist-info/WHEEL
dspy_gepa_logger-0.2.0a0.dist-info/RECORD
