Metadata-Version: 2.4
Name: dspy-gepa-logger
Version: 0.2.0a0
Summary: Comprehensive logging and visualization infrastructure for DSPy GEPA optimization runs
Project-URL: Homepage, https://github.com/raveeshbhalla/dspy-gepa-logger
Project-URL: Repository, https://github.com/raveeshbhalla/dspy-gepa-logger
Project-URL: Issues, https://github.com/raveeshbhalla/dspy-gepa-logger/issues
Author: Raveesh
License-Expression: MIT
Keywords: dspy,gepa,llm,logging,optimization,prompt-optimization
Classifier: Development Status :: 3 - Alpha
Classifier: Intended Audience :: Developers
Classifier: License :: OSI Approved :: MIT License
Classifier: Programming Language :: Python :: 3
Classifier: Programming Language :: Python :: 3.10
Classifier: Programming Language :: Python :: 3.11
Classifier: Programming Language :: Python :: 3.12
Classifier: Topic :: Scientific/Engineering :: Artificial Intelligence
Requires-Python: >=3.10
Requires-Dist: dspy>=2.5.0
Requires-Dist: gepa>=0.0.22
Requires-Dist: pandas>=2.0.0
Requires-Dist: requests>=2.28.0
Provides-Extra: dev
Requires-Dist: black>=23.0.0; extra == 'dev'
Requires-Dist: pytest-asyncio>=0.21.0; extra == 'dev'
Requires-Dist: pytest>=7.0.0; extra == 'dev'
Requires-Dist: ruff>=0.1.0; extra == 'dev'
Provides-Extra: mlflow
Requires-Dist: mlflow>=2.0.0; extra == 'mlflow'
